edc_locator/__init__.py
edc_locator/action_items.py
edc_locator/admin.py
edc_locator/admin_site.py
edc_locator/apps.py
edc_locator/auths.py
edc_locator/exceptions.py
edc_locator/fieldsets.py
edc_locator/modeladmin_mixins.py
edc_locator/models.py
edc_locator/offline_models.py
edc_locator/urls.py
edc_locator/utils.py
edc_locator/forms/__init__.py
edc_locator/forms/subject_locator_form.py
edc_locator/forms/subject_locator_form_validator.py
edc_locator/migrations/0001_initial.py
edc_locator/migrations/0002_auto_20180103_1322.py
edc_locator/migrations/0003_auto_20180103_1351.py
edc_locator/migrations/0004_auto_20180106_2148.py
edc_locator/migrations/0005_auto_20180116_1411.py
edc_locator/migrations/0006_auto_20180116_1528.py
edc_locator/migrations/0007_auto_20180117_1819.py
edc_locator/migrations/0008_auto_20180409_1009.py
edc_locator/migrations/0009_auto_20180708_1954.py
edc_locator/migrations/0010_auto_20180809_0301.py
edc_locator/migrations/0011_auto_20181007_0053.py
edc_locator/migrations/0012_auto_20181010_2121.py
edc_locator/migrations/0013_auto_20181007_0054.py
edc_locator/migrations/0014_auto_20181009_0545.py
edc_locator/migrations/0015_auto_20181010_2125.py
edc_locator/migrations/0016_auto_20181108_0353.py
edc_locator/migrations/0017_auto_20190114_0250.py
edc_locator/migrations/0018_auto_20190305_0123.py
edc_locator/migrations/0019_auto_20190626_1629.py
edc_locator/migrations/0020_auto_20190922_0439.py
edc_locator/migrations/0021_auto_20191024_1000.py
edc_locator/migrations/0022_auto_20200729_2310.py
edc_locator/migrations/0023_auto_20210203_0706.py
edc_locator/migrations/0024_auto_20210911_2036.py
edc_locator/migrations/0025_auto_20220704_1841.py
edc_locator/migrations/0026_alter_historicalsubjectlocator_action_identifier_and_more.py
edc_locator/migrations/0027_auto_20220826_0258.py
edc_locator/migrations/0028_auto_20220826_0322.py
edc_locator/migrations/0029_auto_20220826_0406.py
edc_locator/migrations/0030_auto_20220922_2236.py
edc_locator-1.0.2.dist-info/AUTHORS
edc_locator-1.0.2.dist-info/LICENSE
edc_locator-1.0.2.dist-info/METADATA
edc_locator-1.0.2.dist-info/WHEEL
edc_locator-1.0.2.dist-info/top_level.txt
edc_locator-1.0.2.dist-info/RECORD
